{
  "id": "123",
  "title": "Chapitre 123",
  "text": "Vous roulez bien trop vite pour pouvoir éviter la Type-E. L’Interceptor dérape, crisse, puis bascule dans un spectaculaire tonneau. Sous le choc, les vitres implosent. Le monde tourbillonne autour de vous avant de s’arrêter brusquement, la voiture immobilisée, retournée, dans un nuage de poussière et d’huile brûlée. Suspendu la tête en bas, retenu seulement par votre ceinture, vous distinguez, à travers le sang qui perle sur votre front, plusieurs silhouettes qui s’approchent. Léonardi et ses hommes ne perdent pas de temps : ils vous extirpent de la carcasse, sans ménagement. À demi-conscient, incapable de bouger, vous regardez impuissant alors qu’ils fouillent l’Interceptor pour récupérer tous vos effets personnels ainsi que tout ce qui peut encore avoir de la valeur dans le véhicule détruit. Puis, sans un regard en arrière, ils s’éloignent, vous laissant là, brisé, seul, au milieu du désert brûlant. Le soleil tape, la poussière vous emplit la bouche. Déjà, les premiers vautours tournent au-dessus de vous, attirés par l’odeur du sang et de la défaite. Votre mission s’arrête ici, perdu, abandonné à une mort lente et silencieuse.",
  "image": "/images/chap1.jpg",
  "choices": []
}
